README.rst
setup.cfg
setup.py
test/__init__.py
test/test_weary.py
weary/__init__.py
weary/context.py
weary/method_registrations.py
weary/model_definition.py
weary/property_definition.py
weary/py.typed
weary.egg-info/PKG-INFO
weary.egg-info/SOURCES.txt
weary.egg-info/dependency_links.txt
weary.egg-info/top_level.txt