Metadata-Version: 1.0
Name: weary
Version: 1.2.0
Summary: weary
Home-page: UNKNOWN
Author: Bogdan Mustiata
Author-email: bogdan.mustiata@gmail.com
License: BSD
Platform: UNKNOWN
